<annotation>
	<folder>1</folder>
	<filename>027WL_SC02_SF1309606795158+SF1319793756322_20211122015805271_0227_UP01_1230668239_MR_00.jpg</filename>
	<path>E:\BaiduNetdiskDownload\ICR_EXT\1\027WL_SC02_SF1309606795158+SF1319793756322_20211122015805271_0227_UP01_1230668239_MR_00.jpg</path>
	<source>
		<database>Unknown</database>
	</source>
	<size>
		<width>8192</width>
		<height>7149</height>
		<depth>1</depth>
	</size>
	<segmented>0</segmented>
	<object>
		<name>box</name>
		<pose>Unspecified</pose>
		<truncated>0</truncated>
		<difficult>0</difficult>
		<bndbox>
			<xmin>53</xmin>
			<ymin>3358</ymin>
			<xmax>2899</xmax>
			<ymax>6728</ymax>
		</bndbox>
	</object>
	<object>
		<name>box</name>
		<pose>Unspecified</pose>
		<truncated>0</truncated>
		<difficult>0</difficult>
		<bndbox>
			<xmin>1946</xmin>
			<ymin>81</ymin>
			<xmax>7276</xmax>
			<ymax>6220</ymax>
		</bndbox>
	</object>
</annotation>
